realib/__init__.py
realib-0.1.0.dist-info/METADATA
realib-0.1.0.dist-info/WHEEL
realib-0.1.0.dist-info/RECORD
