Metadata-Version: 2.1
Name: realib
Version: 0.1.0
Summary: 
Author: swjupudi
Author-email: swarna.s92@gmail.com
Requires-Python: >=3.9,<4.0
Classifier: Programming Language :: Python :: 3
Classifier: Programming Language :: Python :: 3.9
Classifier: Programming Language :: Python :: 3.10
Classifier: Programming Language :: Python :: 3.11
Requires-Dist: dash (>=2.7.1,<3.0.0)
Requires-Dist: pandas (>=1.5.2,<2.0.0)
Requires-Dist: plotly (>=5.11.0,<6.0.0)
